simple_rest_client/__init__.py
simple_rest_client/api.py
simple_rest_client/decorators.py
simple_rest_client/exceptions.py
simple_rest_client/models.py
simple_rest_client/request.py
simple_rest_client/resource.py
simple_rest_client-1.2.1.dist-info/LICENSE
simple_rest_client-1.2.1.dist-info/METADATA
simple_rest_client-1.2.1.dist-info/WHEEL
simple_rest_client-1.2.1.dist-info/top_level.txt
simple_rest_client-1.2.1.dist-info/RECORD
