Metadata-Version: 2.1
Name: simple-rest-client
Version: 1.2.1
Summary: Simple REST client for python 3.8+
Home-page: https://github.com/allisson/python-simple-rest-client
Author: Allisson Azevedo
Author-email: allisson@gmail.com
Keywords: rest client http httpx asyncio
Classifier: Development Status :: 3 - Alpha
Classifier: Intended Audience :: Developers
Classifier: Programming Language :: Python :: 3.8
Classifier: Programming Language :: Python :: 3.9
Classifier: Programming Language :: Python :: 3.10
Classifier: Programming Language :: Python :: 3.11
Classifier: Programming Language :: Python :: 3.12
Classifier: Topic :: Software Development :: Libraries
License-File: LICENSE
Requires-Dist: python-status >=1.0.1
Requires-Dist: httpx >=0.23.0
Requires-Dist: python-slugify >=6.1.2
